LICENSE.txt
MANIFEST.in
README.md
README.rst
setup.cfg
setup.py
TheMixed/TheMixed.py
TheMixed/__init__.py
TheMixed.egg-info/PKG-INFO
TheMixed.egg-info/SOURCES.txt
TheMixed.egg-info/dependency_links.txt
TheMixed.egg-info/top_level.txt
TheMixed/XMLcollection1/PMC8499788.xml
TheMixed/XMLcollection1/PMC8755319.xml
TheMixed/XMLcollection1/PMC8934712.xml
TheMixed/XMLcollection1/PMC9242688.xml
TheMixed/XMLcollection1/PMC9242884.xml
TheMixed/XMLcollection1/PMC9277988.xml
TheMixed/XMLcollection1/PMC9278083.xml
TheMixed/XMLcollection1/PMC9278178.xml
TheMixed/XMLcollection1/PMC9281458.xml
TheMixed/XMLcollection1/PMC9281590.xml
TheMixed/XMLcollection1/PMC9283122.xml
TheMixed/XMLcollection1/PMC9284567.xml
TheMixed/XMLcollection1/PMC9284599.xml
TheMixed/XMLcollection1/PMC9285112.xml
TheMixed/XMLcollection1/PMC9287470.xml
TheMixed/XMLcollection1/PMC9289581.xml
TheMixed/XMLcollection1/PMC9289664.xml
TheMixed/XMLcollection1/PMC9290425.xml
TheMixed/XMLcollection1/PMC9291241.xml
TheMixed/XMLcollection1/PMC9295334.xml
TheMixed/XMLcollection1/PMC9295375.xml
TheMixed/XMLcollection1/PMC9295384.xml
TheMixed/XMLcollection1/PMC9295679.xml
TheMixed/XMLcollection1/PMC9296900.xml
TheMixed/XMLcollection1/PMC9298167.xml
TheMixed/XMLcollection1/PMC9298468.xml
TheMixed/XMLcollection1/PMC9298551.xml
TheMixed/XMLcollection1/PMC9298711.xml
TheMixed/XMLcollection1/PMC9302868.xml
TheMixed/XMLcollection1/PMC9307220.xml
TheMixed/XMLcollection1/PMC9308500.xml
TheMixed/XMLcollection1/PMC9308998.xml
TheMixed/XMLcollection1/PMC9309232.xml
TheMixed/XMLcollection1/PMC9310363.xml
TheMixed/XMLcollection1/PMC9311342.xml
TheMixed/XMLcollection1/PMC9312374.xml
TheMixed/XMLcollection1/PMC9312732.xml
TheMixed/XMLcollection1/PMC9312909.xml
TheMixed/XMLcollection1/PMC9313162.xml
TheMixed/XMLcollection1/PMC9313938.xml
TheMixed/XMLcollection1/PMC9314237.xml
TheMixed/XMLcollection1/PMC9315516.xml
TheMixed/XMLcollection1/PMC9322618.xml
TheMixed/XMLcollection1/PMC9325633.xml
TheMixed/XMLcollection1/PMC9326076.xml
TheMixed/XMLcollection1/PMC9326230.xml
TheMixed/XMLcollection1/PMC9326243.xml
TheMixed/XMLcollection1/PMC9326247.xml
